{
  "slug": "7379e0db",
  "video_id": "UjAJ2jKH_QM",
  "movie_title": "Why Do We Itch?",
  "movie_url": "https://youtu.be/UjAJ2jKH_QM",
  "published_at": "2025-04-17T14:00:44Z",
  "duration": "PT1M1S",
  "tags": [
    "kurzgezagt",
    "kurzgesatg",
    "kurzgsagt",
    "kurzgessagt",
    "kurzgesagtz",
    "kurzgazagt",
    "kurzgesaagt",
    "curzgesagt",
    "kurzgesakt",
    "kurzgesaht",
    "kurzgesagt",
    "krzgesagt",
    "kurgesaht",
    "kurzgesaght",
    "kurtzgesagt",
    "kurzgsat",
    "kurzsagt",
    "kurz",
    "kurg",
    "kurs",
    "kuzz",
    "curz",
    "krz",
    "kurzz",
    "kurzt",
    "kurzg",
    "kgs",
    "ksg",
    "kgz",
    "kszt",
    "krgs",
    "kzgs",
    "kzs",
    "krs"
  ],
  "introduction": "Why do we itch and why does scratching feel so good? Itching evolved to protect us, but for 1 in 5 p",
  "lead_intro": "Learn about the fascinating world of itching and its importance in survival across various species.",
  "quiz": [
    {
      "question": "What releases the feel-good hormone serotonin when you scratch an itch?",
      "choices": [
        "nerve cells",
        "muscles",
        "spinal cord"
      ],
      "answer": "muscles",
      "explanation": "Scratching an itch sends a signal to your muscles, which then release the feel-good hormone serotonin."
    },
    {
      "question": "Approximately how many people suffer from chronic itch?",
      "choices": [
        "one in ten",
        "one in four",
        "one in five"
      ],
      "answer": "one in five",
      "explanation": "Around one in five people suffer from chronic itch at least once."
    },
    {
      "question": "What can help calm an overactive itch in chronic cases?",
      "choices": [
        "medication",
        "exercise",
        "diet"
      ],
      "answer": "medication",
      "explanation": "Medications and stress management can help calm an overactive itch in chronic cases."
    },
    {
      "question": "What is a potential side effect of some medicines mentioned in the text?",
      "choices": [
        "increased appetite",
        "lowered drug dose",
        "better sleep"
      ],
      "answer": "lowered drug dose",
      "explanation": "Some medicines can cause itching as a side effect, leading individuals to lower their dose of life-saving drugs."
    },
    {
      "question": "What triggers itching besides bugs and bites according to the text?",
      "choices": [
        "weather changes",
        "psychological causes",
        "loud noises"
      ],
      "answer": "psychological causes",
      "explanation": "Itching can be triggered by a range of causes, including psychological factors, besides bugs and bites."
    }
  ]
}