{
  "slug": "bf61d705",
  "video_id": "2dAp1PmhH8g",
  "channel_name": "neo",
  "movie_title": "The Battle for Las Vegas",
  "movie_url": "https://youtu.be/2dAp1PmhH8g",
  "published_at": "2023-03-07T14:01:00Z",
  "duration": "PT17M57S",
  "introduction": "Get Nebula using my link for 40% off an annual subscription: https://go.nebula.tv/neo\n\nMy next video",
  "thumbnail_url": "https://i.ytimg.com/vi/2dAp1PmhH8g/default.jpg",
  "category": "",
  "tags": [
    "las vegas",
    "business",
    "gambling",
    "casears",
    "caesars entertainement",
    "mgm grand",
    "mgm growth properties",
    "mgm resorts international",
    "economic",
    "financial",
    "finance",
    "real estate",
    "holding",
    "investment",
    "stock",
    "vici properties",
    "understanding",
    "explained",
    "neo",
    "flamingo hotel",
    "luxor",
    "mandalay bay",
    "resort",
    "casino",
    "poker",
    "history"
  ],
  "views": "",
  "likes": "",
  "subtitle_status": "",
  "vocabulary": [
    {
      "word": "opulence",
      "definition": "great wealth or luxuriousness",
      "example": "The Mandalay Bay Resort focuses on opulence with its gold-colored glass facade."
    },
    {
      "word": "mergers",
      "definition": "the combining of two or more companies into a single company",
      "example": "The current situation in Las Vegas is the result of decades of mergers and acquisitions."
    },
    {
      "word": "acquisitions",
      "definition": "the process of buying or taking control of another company or its assets",
      "example": "MGM Grand acquired Mirage Resorts in 2000 through acquisitions."
    },
    {
      "word": "leveraged buyout",
      "definition": "the acquisition of a company using a significant amount of borrowed money",
      "example": "The complex takeover of Caesars Entertainment involved a leveraged buyout."
    },
    {
      "word": "restructure",
      "definition": "to organize a company, business, or system in a new way to make it operate more effectively",
      "example": "Caesars Entertainment underwent a complex restructure after facing financial challenges."
    },
    {
      "word": "real estate investment trust (REIT)",
      "definition": "a company that owns, operates, or finances income-producing real estate",
      "example": "VICI Properties is a real estate investment trust that owns the land and buildings of various hotels in Las Vegas."
    }
  ]
}