{
  "slug": "fffc489a",
  "video_id": "sNhhvQGsMEc",
  "channel_name": "Kurzgesagt – In a Nutshell",
  "movie_title": "The Fermi Paradox — Where Are All The Aliens? (1/2)",
  "movie_url": "https://youtu.be/sNhhvQGsMEc",
  "published_at": "2015-05-06T12:55:55Z",
  "duration": "PT6M21S",
  "introduction": "The universe is unbelievably big – trillions of stars and even more planets. Soo… there just has to",
  "thumbnail_url": "https://i.ytimg.com/vi/sNhhvQGsMEc/default.jpg",
  "category": "",
  "tags": [
    "Fermi paradox",
    "Enrico Fermi (Academic)",
    "Physics (Field Of Study)",
    "aliens",
    "death",
    "Ufo",
    "Space",
    "Alien",
    "space ship",
    "Planet",
    "Predator",
    "science",
    "science fiction",
    "solution",
    "great filter",
    "documentary",
    "war",
    "stars",
    "universe",
    "tape",
    "genesis",
    "destruction",
    "god",
    "Kardashev scale",
    "set",
    "debate",
    "definition",
    "solved",
    "sun",
    "interstellar",
    "galaxy",
    "mars",
    "earth",
    "facts",
    "wait but why",
    "firefly",
    "doctor who",
    "masters of orion",
    "Milky Way (Galaxy)",
    "star gate",
    "borg",
    "star wars",
    "Star trek",
    "Vsauce",
    "infographic",
    "animation",
    "kurzgesagt",
    "in a nutshell"
  ],
  "views": "",
  "likes": "",
  "subtitle_status": "",
  "vocabulary": [
    {
      "word": "observable",
      "definition": "able to be seen or noticed",
      "example": "The observable universe is vast and full of mysteries."
    },
    {
      "word": "habitable",
      "definition": "suitable or good enough to live in",
      "example": "Scientists search for habitable planets outside our solar system."
    },
    {
      "word": "paradox",
      "definition": "a statement or situation that may be true but seems to be impossible or difficult to understand",
      "example": "The Fermi paradox questions the existence of extraterrestrial civilizations."
    },
    {
      "word": "civilization",
      "definition": "an advanced stage of human social development and organization",
      "example": "A type 3 civilization would control its entire galaxy."
    },
    {
      "word": "overcome",
      "definition": "succeed in dealing with a problem or difficulty",
      "example": "Humanity must overcome great challenges to reach the stars."
    },
    {
      "word": "moist",
      "definition": "slightly wet, damp, or humid",
      "example": "The tiny planet was covered in moist soil and lush vegetation."
    }
  ]
}