{
  "slug": "16c2db88",
  "video_id": "K-9-dtJpZ9c",
  "channel_name": "BBC Learning English",
  "movie_title": "Learning lessons from the Moon ⏲️ 6 Minute English",
  "movie_url": "https://youtu.be/K-9-dtJpZ9c",
  "published_at": "2023-12-21T15:00:12Z",
  "duration": "PT6M24S",
  "introduction": "Summer 2023 saw two missions to the Moon. Why are scientists so keen to get there? Find out with Geo",
  "thumbnail_url": "https://i.ytimg.com/vi/K-9-dtJpZ9c/default.jpg",
  "category": "",
  "tags": [
    "learn English",
    "English vocabulary",
    "speak English",
    "bbc english",
    "English teacher",
    "英語",
    "영어",
    "อังกฤษ",
    "Anh",
    "English tutorial",
    "English grammar",
    "IELTS",
    "British English",
    "English pronunciation",
    "English lesson",
    "idiom",
    "English expressions",
    "BBC Learning English",
    "slang",
    "English speaking",
    "ELT",
    "podcast",
    "Ingilizce",
    "bbc",
    "bbc learning english",
    "English class",
    "6 minute",
    "English speaking practice",
    "English words",
    "English podcast",
    "podcast English"
  ],
  "views": "",
  "likes": "",
  "subtitle_status": "",
  "vocabulary": [
    {
      "word": "inert",
      "definition": "not moving or unable to move",
      "example": "The rock on the moon is inert and remains unchanged for billions of years."
    },
    {
      "word": "crater",
      "definition": "a very large hole in the ground",
      "example": "The moon's surface is covered with craters caused by impacts from space objects."
    },
    {
      "word": "pockmarked",
      "definition": "marked by small holes and scars",
      "example": "The pockmarked surface of the moon reveals its history of impacts over billions of years."
    },
    {
      "word": "a big deal",
      "definition": "important or significant",
      "example": "The discovery of water on the moon is indeed a big deal for scientists researching Earth's origins."
    },
    {
      "word": "trace something back",
      "definition": "to discover the causes of something by investigating how it developed",
      "example": "Scientists are tracing back the origins of lunar water to understand its impact on Earth."
    },
    {
      "word": "a smoking gun",
      "definition": "indisputable evidence or conclusive proof of something",
      "example": "Finding water on the moon could be the smoking gun confirming its role in Earth's water formation."
    }
  ]
}