{
  "slug": "6d6478be",
  "video_id": "hX_acKX1G2Y",
  "channel_name": "Kurzgesagt – In a Nutshell",
  "movie_title": "The Sun is NOT Yellow!",
  "movie_url": "https://youtu.be/hX_acKX1G2Y",
  "published_at": "2024-08-01T14:00:40Z",
  "duration": "PT1M",
  "introduction": "Repeat after us: 🗣️🗣️🗣️🗣️The. Sun. Is. Not. Yellow. ‼️‼️‼️‼️ \n\n#kurzgesagt\n#inanutshell #kurzges",
  "thumbnail_url": "https://i.ytimg.com/vi/hX_acKX1G2Y/default.jpg",
  "category": "",
  "tags": [
    "inanutshell",
    "kurzgesagt",
    "kurzgesagt_inanutshell",
    "learnwithshorts",
    "interestingfact",
    "kurzgesagt - in a nutshell",
    "in a nutshell",
    "science facts",
    "Learn with Shorts",
    "science",
    "YouTube university",
    "YouTube MBA",
    "sun",
    "physics",
    "color studies",
    "colors",
    "is the sun yellow"
  ],
  "views": "",
  "likes": "",
  "subtitle_status": "",
  "vocabulary": [
    {
      "word": "prism",
      "definition": "a transparent object that separates white light into a spectrum of colors",
      "example": "The scientist used a prism to demonstrate how sunlight can be separated into different colors."
    },
    {
      "word": "radiates",
      "definition": "emits or gives off (energy, such as light or heat)",
      "example": "The sun radiates heat and light, providing energy to Earth."
    },
    {
      "word": "spectrum",
      "definition": "the range of colors produced when light is separated by a prism, or a range of related ideas or qualities",
      "example": "The rainbow displays a spectrum of colors, from red to violet."
    },
    {
      "word": "transparent",
      "definition": "clear, see-through; allowing light to pass through so that objects behind can be distinctly seen",
      "example": "The glass in the window is transparent, allowing sunlight to enter the room."
    },
    {
      "word": "wavelengths",
      "definition": "the distance between two successive crests of a wave, especially points in a sound or electromagnetic wave",
      "example": "Different colors of light have different wavelengths; red light has a longer wavelength than blue light."
    },
    {
      "word": "scatter",
      "definition": "to cause light to pass in many directions, making the light appear to twinkle or shimmer",
      "example": "The clouds scatter sunlight, creating a beautiful display of colors in the sky."
    }
  ]
}