{
  "slug": "fbc42515",
  "video_id": "xf2RF9vx-G4",
  "channel_name": "BBC Learning English",
  "movie_title": "Space saving solar hacks ⏲️ 6 Minute English",
  "movie_url": "https://youtu.be/xf2RF9vx-G4",
  "published_at": "2023-09-07T14:02:01Z",
  "duration": "PT6M24S",
  "introduction": "Solar power is key for meeting net-zero targets, but how can we find space to build more solar panel",
  "thumbnail_url": "https://i.ytimg.com/vi/xf2RF9vx-G4/default.jpg",
  "category": "",
  "tags": [
    "learn English",
    "English vocabulary",
    "speak English",
    "bbc english",
    "English teacher",
    "英語",
    "영어",
    "อังกฤษ",
    "Anh",
    "English tutorial",
    "English grammar",
    "IELTS",
    "British English",
    "English pronunciation",
    "English lesson",
    "idiom",
    "English expressions",
    "BBC Learning English",
    "slang",
    "English speaking",
    "ELT",
    "podcast",
    "Ingilizce",
    "bbc",
    "bbc learning english",
    "English class",
    "6 minute",
    "English speaking practice",
    "English words",
    "English podcast",
    "podcast English"
  ],
  "views": "",
  "likes": "",
  "subtitle_status": "",
  "vocabulary": [
    {
      "word": "canopy",
      "definition": "a cover fixed over something to provide shelter or decoration",
      "example": "The canopy over the outdoor dining area protected customers from the sun."
    },
    {
      "word": "enticing",
      "definition": "attractive because it offers advantages or pleasures",
      "example": "The enticing offer of a free trial encouraged many people to sign up."
    },
    {
      "word": "tumbled",
      "definition": "decreased quickly in a short time",
      "example": "After the announcement, the stock prices tumbled rapidly."
    },
    {
      "word": "economically feasible",
      "definition": "the economic advantages achieved are greater than the economic costs",
      "example": "The project became economically feasible once they secured a stable source of funding."
    },
    {
      "word": "parabolic",
      "definition": "having the form or mathematical properties of a parabola",
      "example": "The parabolic mirror was used to focus sunlight onto the solar panel."
    },
    {
      "word": "mirroring",
      "definition": "reflecting something, especially in a way that gives the appearance of a mirror",
      "example": "The design of the building included mirroring windows to reduce heat absorption."
    }
  ]
}