{
  "slug": "be9c362b",
  "video_id": "5sVfTPaxRwk",
  "channel_name": "Kurzgesagt – In a Nutshell",
  "movie_title": "If You Eat Meat You Should Know This",
  "movie_url": "https://youtu.be/5sVfTPaxRwk",
  "published_at": "2025-02-25T15:00:01Z",
  "duration": "PT15M30S",
  "introduction": "Are you getting the full story? Go to https://ground.news/KiN to access world-wide sources and compa",
  "thumbnail_url": "https://i.ytimg.com/vi/5sVfTPaxRwk/default.jpg",
  "category": "",
  "tags": [],
  "views": "",
  "likes": "",
  "subtitle_status": "",
  "vocabulary": [
    {
      "word": "ingrained",
      "definition": "firmly established and difficult to change",
      "example": "Meat consumption is ingrained in our culture."
    },
    {
      "word": "lectured",
      "definition": "reprimanded or scolded at length, often in a critical or tedious way",
      "example": "Nobody likes to be morally lectured about their food choices."
    },
    {
      "word": "anesthesia",
      "definition": "a medical treatment that prevents patients from feeling pain during surgery or other procedures",
      "example": "Anesthesia is used for the castration of pigs in some farming practices."
    },
    {
      "word": "pseudo",
      "definition": "not genuine; falsely resembling something",
      "example": "Some labels claiming to be 'natural' are merely pseudo-signs in the food industry."
    },
    {
      "word": "nuance",
      "definition": "a subtle difference or distinction in expression, meaning, response, etc.",
      "example": "Understanding the nuance of different perspectives is crucial for making informed decisions."
    },
    {
      "word": "curtail",
      "definition": "to reduce in extent or quantity; impose a restriction on",
      "example": "Consumers curtailed their spending on meat after learning about the inhumane treatment of animals."
    }
  ]
}