{
  "slug": "93bb445a",
  "video_id": "dqwpQarrDwk",
  "channel_name": "Kurzgesagt – In a Nutshell",
  "movie_title": "1,000km Cable to the Stars - The Skyhook",
  "movie_url": "https://youtu.be/dqwpQarrDwk",
  "published_at": "2019-11-17T13:30:03Z",
  "published_date": "2025-07-04T20:13:06.220765",
  "duration": "PT7M",
  "introduction": "Sources: https://sites.google.com/view/sources-skyhooks/\n\nGet your 12,020 SPACE Calendar here: https",
  "thumbnail_url": "https://i.ytimg.com/vi/dqwpQarrDwk/default.jpg",
  "category": "",
  "tags": [
    "Skyhook",
    "Spacetether",
    "Tether",
    "Space",
    "Spavetravel",
    "Rocket",
    "Spaceship",
    "Rocketfuel",
    "Earth",
    "Earthorbit",
    "Infrastructure",
    "Fuel",
    "Payload",
    "Moon",
    "Mars",
    "Space Elevator",
    "Cable",
    "Weight",
    "Counter weight",
    "Nylon",
    "Debris",
    "Meteorit",
    "Orbit",
    "Atmosphere",
    "Cost",
    "Speed",
    "Momentum",
    "Phobos",
    "Deimos",
    "Mars Moon",
    "Jupiter",
    "Saturn",
    "Venus",
    "Mercury",
    "Solarsystem",
    "Asteroid Mining",
    "sky hook"
  ],
  "views": "",
  "likes": "",
  "subtitle_status": "",
  "assigned_category": "science",
  "assigned_level": "advanced"
}