{
  "slug": "bb85ed71",
  "video_id": "MUWUHf-rzks",
  "channel_name": "Kurzgesagt – In a Nutshell",
  "movie_title": "How to Make an Elephant Explode – The Size of Life 2",
  "movie_url": "https://youtu.be/MUWUHf-rzks",
  "published_at": "2017-12-21T13:38:50Z",
  "published_date": "2025-07-04T20:13:11.442184",
  "duration": "PT6M55S",
  "introduction": "OUR CHANNELS\n▀▀▀▀▀▀▀▀▀▀▀▀▀▀▀▀▀▀▀▀▀▀▀▀▀▀\nGerman Channel: https://kgs.link/youtubeDE \nSpanish Channel:",
  "thumbnail_url": "https://i.ytimg.com/vi/MUWUHf-rzks/default.jpg",
  "category": "",
  "tags": [
    "size",
    "elephant",
    "mouse",
    "exploding",
    "animals",
    "life",
    "wounder",
    "kleibers law",
    "scaling",
    "pregnant",
    "children",
    "metabolism",
    "animation",
    "kurzgesagt",
    "infographic",
    "funny",
    "in a nutshell"
  ],
  "views": "",
  "likes": "",
  "subtitle_status": "",
  "assigned_category": "science",
  "assigned_level": "advanced"
}