{
  "slug": "e082f238",
  "video_id": "zKzT9BsbBJ4",
  "channel_name": "Vogue",
  "movie_title": "Can Sadie Sink Finish These Broadway Lyrics?",
  "movie_url": "https://youtu.be/zKzT9BsbBJ4",
  "published_at": "2025-06-11T16:00:02Z",
  "published_date": "2025-06-24T00:13:51.618372",
  "duration": "PT21S",
  "introduction": "At the 2025 Tony Awards, Sadie Sink tries to finish some famous lyrics from Broadway musicals.\n\nStil",
  "thumbnail_url": "https://i.ytimg.com/vi/zKzT9BsbBJ4/default.jpg",
  "category": "",
  "tags": [
    "broadway",
    "broadway interview",
    "broadway musical tonys",
    "broadway vogue",
    "broadway vogue interview",
    "sadie",
    "sadie sink broadway",
    "sadie sink vogue",
    "sadie sink vogue interview",
    "tony awards",
    "tonys",
    "tonys musical",
    "vertical-video",
    "vogue",
    "vogue broadway",
    "vogue sadie sink"
  ],
  "views": "",
  "likes": "",
  "subtitle_status": "",
  "assigned_category": "conversation",
  "assigned_level": "beginner"
}